brain_sdk/__init__.py
brain_sdk/agent.py
brain_sdk/agent_ai.py
brain_sdk/agent_brain.py
brain_sdk/agent_mcp.py
brain_sdk/agent_registry.py
brain_sdk/agent_server.py
brain_sdk/agent_utils.py
brain_sdk/agent_workflow.py
brain_sdk/async_config.py
brain_sdk/async_execution_manager.py
brain_sdk/client.py
brain_sdk/connection_manager.py
brain_sdk/decorators.py
brain_sdk/did_manager.py
brain_sdk/dynamic_skills.py
brain_sdk/execution_context.py
brain_sdk/execution_state.py
brain_sdk/http_connection_manager.py
brain_sdk/logger.py
brain_sdk/mcp_client.py
brain_sdk/mcp_manager.py
brain_sdk/mcp_stdio_bridge.py
brain_sdk/memory.py
brain_sdk/memory_events.py
brain_sdk/multimodal.py
brain_sdk/multimodal_response.py
brain_sdk/pydantic_utils.py
brain_sdk/rate_limiter.py
brain_sdk/result_cache.py
brain_sdk/router.py
brain_sdk/status.py
brain_sdk/types.py
brain_sdk/utils.py
brain_sdk/vc_generator.py
brain_sdk-0.1.20.dist-info/licenses/LICENSE
brain_sdk-0.1.20.dist-info/METADATA
brain_sdk-0.1.20.dist-info/WHEEL
brain_sdk-0.1.20.dist-info/top_level.txt
brain_sdk-0.1.20.dist-info/RECORD
